extbpy/__init__.py
extbpy/builder.py
extbpy/cli.py
extbpy/exceptions.py
extbpy/platforms.py
extbpy/utils.py
extbpy-0.2.0.dist-info/WHEEL
extbpy-0.2.0.dist-info/entry_points.txt
extbpy-0.2.0.dist-info/METADATA
extbpy-0.2.0.dist-info/RECORD
