Metadata-Version: 2.3
Name: extbpy
Version: 0.2.0
Summary: A powerful CLI tool for building Blender extensions with Python dependencies
Keywords: blender,extension,addon,build,wheels
Author: Brady Johnston
Author-email: Brady Johnston <brady.johnston@me.com>
Classifier: Development Status :: 3 - Alpha
Classifier: Intended Audience :: Developers
Classifier: License :: OSI Approved :: MIT License
Classifier: Operating System :: OS Independent
Classifier: Programming Language :: Python :: 3
Classifier: Programming Language :: Python :: 3.11
Classifier: Programming Language :: Python :: 3.12
Classifier: Topic :: Multimedia :: Graphics :: 3D Modeling
Classifier: Topic :: Software Development :: Build Tools
Requires-Dist: click>=8.0.0
Requires-Dist: rich>=13.0.0
Requires-Dist: tomlkit>=0.11.0
Requires-Dist: packaging>=21.0
Requires-Dist: pytest>=7.0.0 ; extra == 'dev'
Requires-Dist: pytest-cov>=4.0.0 ; extra == 'dev'
Requires-Dist: black>=23.0.0 ; extra == 'dev'
Requires-Dist: ruff>=0.14.9 ; extra == 'dev'
Requires-Dist: mypy>=1.0.0 ; extra == 'dev'
Requires-Python: >=3.11
Project-URL: Homepage, https://github.com/bradyjohnston/extbpy
Project-URL: Issues, https://github.com/bradyajohnston/extbpy/issues
Project-URL: Repository, https://github.com/bradyajohnston/extbpy
Provides-Extra: dev
